deco/__about__.py
deco/__init__.py
deco/_astutil.py
deco/_concurrent.py
deco/_decorator.py
deco/py.typed
deco3-0.9.0.dist-info/licenses/LICENSE
deco3-0.9.0.dist-info/METADATA
deco3-0.9.0.dist-info/WHEEL
deco3-0.9.0.dist-info/top_level.txt
deco3-0.9.0.dist-info/zip-safe
deco3-0.9.0.dist-info/RECORD
