Metadata-Version: 2.4
Name: deco3
Version: 0.9.0
Summary: A decorator for concurrency.
Author: Alex Sherman, Adam Karpierz
Author-email: adam@karpierz.net
Maintainer: Adam Karpierz
Maintainer-email: adam@karpierz.net
License-Expression: MIT
Project-URL: Homepage, https://pypi.org/project/deco3/
Project-URL: Documentation, https://deco3.readthedocs.io/
Project-URL: Download, https://pypi.org/project/deco3/
Project-URL: Source, https://github.com/karpierz/deco3
Project-URL: Issues, https://github.com/karpierz/deco3/issues
Keywords: deco,deco3,concurrency,multiprocessing,multitasking
Platform: any
Classifier: Development Status :: 5 - Production/Stable
Classifier: Intended Audience :: Developers
Classifier: Operating System :: OS Independent
Classifier: Natural Language :: Polish
Classifier: Programming Language :: Python
Classifier: Programming Language :: Python :: 3
Classifier: Programming Language :: Python :: 3.10
Classifier: Programming Language :: Python :: 3.11
Classifier: Programming Language :: Python :: 3.12
Classifier: Programming Language :: Python :: 3.13
Classifier: Programming Language :: Python :: 3.14
Classifier: Programming Language :: Python :: 3 :: Only
Classifier: Programming Language :: Python :: Implementation :: CPython
Classifier: Programming Language :: Python :: Implementation :: PyPy
Classifier: Topic :: Software Development :: Libraries :: Python Modules
Requires-Python: <4.0.0,>=3.10.0
License-File: LICENSE
Requires-Dist: setuptools>=80.9.0
Requires-Dist: pkg-about>=1.4.0
Provides-Extra: doc
Requires-Dist: Sphinx>=8.1.3; extra == "doc"
Requires-Dist: sphinx-autodoc-typehints>=3.0.1; extra == "doc"
Requires-Dist: sphinx-toolbox>=4.0.0; extra == "doc"
Requires-Dist: sphinx-tabs>=3.4.5; extra == "doc"
Requires-Dist: sphinx-copybutton>=0.5.2; extra == "doc"
Requires-Dist: sphinxcontrib-spelling>=8.0.1; extra == "doc"
Requires-Dist: sphinx-lint>=1.0.0; extra == "doc"
Requires-Dist: restructuredtext-lint>=1.4.0; extra == "doc"
Requires-Dist: nbsphinx>=0.9.7; extra == "doc"
Provides-Extra: test
Requires-Dist: deepdiff>=8.6.0; extra == "test"
Requires-Dist: rich>=14.1.0; extra == "test"
Dynamic: license-file
